[
{
  "pk": 1705, 
  "model": "desktop.document2", 
  "fields": {
    "search": null, 
    "uuid": "ea9711d1-9c29-22f6-0922-1e9def8b5880", 
    "extra": "", 
    "type": "oozie-workflow2", 
    "description": "Search over Non-Fraud for Similar Records to Fraud . An expansion of the Potential Fraud Cases", 
    "is_history": false, 
    "parent_directory": [
      "15c3778f-8947-49b8-8a46-cc286ddc553f", 
      1, 
      false
    ], 
    "is_managed": false, 
    "last_modified": "2019-01-31T14:56:01", 
    "version": 1, 
    "owner": [
      "siemanalyst"
    ], 
    "dependencies": [
      [
        "9aa4679c-7aa7-4900-9eed-7c1139a3c293", 
        1, 
        true
      ]
    ], 
    "data": "{\"layout\": [{\"oozieRows\": [{\"enableOozieDropOnBefore\": true, \"enableOozieDropOnSide\": true, \"enableOozieDrop\": false, \"widgets\": [{\"status\": \"\", \"logsURL\": \"\", \"name\": \"Ssh\", \"widgetType\": \"ssh-widget\", \"oozieMovable\": true, \"ooziePropertiesExpanded\": false, \"gridsterHeight\": 0, \"externalIdUrl\": \"\", \"properties\": {}, \"externalId\": \"\", \"isLoading\": false, \"offset\": 0, \"actionURL\": \"\", \"progress\": 0, \"klass\": \"card card-widget span12\", \"oozieExpanded\": false, \"id\": \"e0cfe17b-1240-5be1-1100-d2976f81d60f\", \"size\": 12}], \"id\": \"88de9da2-f239-41e6-79d1-c8dc073c429e\", \"columns\": []}], \"rows\": [{\"enableOozieDropOnBefore\": true, \"enableOozieDropOnSide\": true, \"enableOozieDrop\": false, \"widgets\": [{\"status\": \"\", \"logsURL\": \"\", \"name\": \"Start\", \"widgetType\": \"start-widget\", \"oozieMovable\": false, \"ooziePropertiesExpanded\": false, \"gridsterHeight\": 0, \"externalIdUrl\": \"\", \"properties\": {}, \"externalId\": \"\", \"isLoading\": false, \"offset\": 0, \"actionURL\": \"\", \"progress\": 0, \"klass\": \"card card-widget span12\", \"oozieExpanded\": false, \"id\": \"3f107997-04cc-8733-60a9-a4bb62cebffc\", \"size\": 12}], \"id\": \"05c4c1bc-6c5f-c46c-edb4-dbe71faaf02e\", \"columns\": []}, {\"enableOozieDropOnBefore\": true, \"enableOozieDropOnSide\": true, \"enableOozieDrop\": false, \"widgets\": [{\"status\": \"\", \"logsURL\": \"\", \"name\": \"Ssh\", \"widgetType\": \"ssh-widget\", \"oozieMovable\": true, \"ooziePropertiesExpanded\": false, \"gridsterHeight\": 0, \"externalIdUrl\": \"\", \"properties\": {}, \"externalId\": \"\", \"isLoading\": false, \"offset\": 0, \"actionURL\": \"\", \"progress\": 0, \"klass\": \"card card-widget span12\", \"oozieExpanded\": false, \"id\": \"e0cfe17b-1240-5be1-1100-d2976f81d60f\", \"size\": 12}], \"id\": \"88de9da2-f239-41e6-79d1-c8dc073c429e\", \"columns\": []}, {\"enableOozieDropOnBefore\": true, \"enableOozieDropOnSide\": true, \"enableOozieDrop\": false, \"widgets\": [{\"status\": \"\", \"logsURL\": \"\", \"name\": \"End\", \"widgetType\": \"end-widget\", \"oozieMovable\": false, \"ooziePropertiesExpanded\": false, \"gridsterHeight\": 0, \"externalIdUrl\": \"\", \"properties\": {}, \"externalId\": \"\", \"isLoading\": false, \"offset\": 0, \"actionURL\": \"\", \"progress\": 0, \"klass\": \"card card-widget span12\", \"oozieExpanded\": false, \"id\": \"33430f0f-ebfa-c3ec-f237-3e77efa03d0a\", \"size\": 12}], \"id\": \"2c0d65b1-ef8d-f101-53f7-3426b0a6a1a3\", \"columns\": []}, {\"enableOozieDropOnBefore\": true, \"enableOozieDropOnSide\": true, \"enableOozieDrop\": false, \"widgets\": [{\"status\": \"\", \"logsURL\": \"\", \"name\": \"Kill\", \"widgetType\": \"kill-widget\", \"oozieMovable\": true, \"ooziePropertiesExpanded\": false, \"gridsterHeight\": 0, \"externalIdUrl\": \"\", \"properties\": {}, \"externalId\": \"\", \"isLoading\": false, \"offset\": 0, \"actionURL\": \"\", \"progress\": 0, \"klass\": \"card card-widget span12\", \"oozieExpanded\": false, \"id\": \"17c9c895-5a16-7443-bb81-f34b30b21548\", \"size\": 12}], \"id\": \"9f831f09-4591-1bfe-7c4e-8194fe8b522b\", \"columns\": []}], \"oozieEndRow\": {\"enableOozieDropOnBefore\": true, \"enableOozieDropOnSide\": true, \"enableOozieDrop\": false, \"widgets\": [{\"status\": \"\", \"logsURL\": \"\", \"name\": \"End\", \"widgetType\": \"end-widget\", \"oozieMovable\": false, \"ooziePropertiesExpanded\": false, \"gridsterHeight\": 0, \"externalIdUrl\": \"\", \"properties\": {}, \"externalId\": \"\", \"isLoading\": false, \"offset\": 0, \"actionURL\": \"\", \"progress\": 0, \"klass\": \"card card-widget span12\", \"oozieExpanded\": false, \"id\": \"33430f0f-ebfa-c3ec-f237-3e77efa03d0a\", \"size\": 12}], \"id\": \"2c0d65b1-ef8d-f101-53f7-3426b0a6a1a3\", \"columns\": []}, \"oozieKillRow\": {\"enableOozieDropOnBefore\": true, \"enableOozieDropOnSide\": true, \"enableOozieDrop\": false, \"widgets\": [{\"status\": \"\", \"logsURL\": \"\", \"name\": \"Kill\", \"widgetType\": \"kill-widget\", \"oozieMovable\": true, \"ooziePropertiesExpanded\": false, \"gridsterHeight\": 0, \"externalIdUrl\": \"\", \"properties\": {}, \"externalId\": \"\", \"isLoading\": false, \"offset\": 0, \"actionURL\": \"\", \"progress\": 0, \"klass\": \"card card-widget span12\", \"oozieExpanded\": false, \"id\": \"17c9c895-5a16-7443-bb81-f34b30b21548\", \"size\": 12}], \"id\": \"9f831f09-4591-1bfe-7c4e-8194fe8b522b\", \"columns\": []}, \"enableOozieDropOnAfter\": true, \"oozieStartRow\": {\"enableOozieDropOnBefore\": true, \"enableOozieDropOnSide\": true, \"enableOozieDrop\": false, \"widgets\": [{\"status\": \"\", \"logsURL\": \"\", \"name\": \"Start\", \"widgetType\": \"start-widget\", \"oozieMovable\": false, \"ooziePropertiesExpanded\": false, \"gridsterHeight\": 0, \"externalIdUrl\": \"\", \"properties\": {}, \"externalId\": \"\", \"isLoading\": false, \"offset\": 0, \"actionURL\": \"\", \"progress\": 0, \"klass\": \"card card-widget span12\", \"oozieExpanded\": false, \"id\": \"3f107997-04cc-8733-60a9-a4bb62cebffc\", \"size\": 12}], \"id\": \"05c4c1bc-6c5f-c46c-edb4-dbe71faaf02e\", \"columns\": []}, \"klass\": \"card card-home card-column span12\", \"enableOozieDropOnBefore\": true, \"drops\": [\"temp\"], \"id\": \"5c38d92a-7f94-eb71-fe13-3ba0ba9e7f74\", \"size\": 12}], \"workflow\": {\"properties\": {\"job_xml\": \"\", \"description\": \"Search over Non-Fraud for Similar Records to Fraud . An expansion of the Potential Fraud Cases\", \"parameters\": [{\"name\": \"oozie.use.system.libpath\", \"value\": true}], \"sla_enabled\": false, \"deployment_dir\": \"/user/hue/oozie/workspaces/hue-oozie-1548946440.95\", \"schema_version\": \"uri:oozie:workflow:0.5\", \"sla\": [{\"value\": false, \"key\": \"enabled\"}, {\"value\": \"${nominal_time}\", \"key\": \"nominal-time\"}, {\"value\": \"\", \"key\": \"should-start\"}, {\"value\": \"${30 * MINUTES}\", \"key\": \"should-end\"}, {\"value\": \"\", \"key\": \"max-duration\"}, {\"value\": \"\", \"key\": \"alert-events\"}, {\"value\": \"\", \"key\": \"alert-contact\"}, {\"value\": \"\", \"key\": \"notification-msg\"}, {\"value\": \"\", \"key\": \"upstream-apps\"}], \"show_arrows\": true, \"wf1_id\": null, \"properties\": []}, \"name\": \"Execute - Fraud -  AUTOML - Daily\", \"hasKillNode\": true, \"versions\": [\"uri:oozie:workflow:0.4\", \"uri:oozie:workflow:0.4.5\", \"uri:oozie:workflow:0.5\"], \"isDirty\": false, \"movedNode\": null, \"linkMapping\": {\"33430f0f-ebfa-c3ec-f237-3e77efa03d0a\": [], \"e0cfe17b-1240-5be1-1100-d2976f81d60f\": [\"33430f0f-ebfa-c3ec-f237-3e77efa03d0a\"], \"3f107997-04cc-8733-60a9-a4bb62cebffc\": [\"e0cfe17b-1240-5be1-1100-d2976f81d60f\"], \"17c9c895-5a16-7443-bb81-f34b30b21548\": []}, \"nodeIds\": [\"3f107997-04cc-8733-60a9-a4bb62cebffc\", \"33430f0f-ebfa-c3ec-f237-3e77efa03d0a\", \"17c9c895-5a16-7443-bb81-f34b30b21548\", \"e0cfe17b-1240-5be1-1100-d2976f81d60f\"], \"nodes\": [{\"name\": \"Start\", \"associatedDocumentLoading\": true, \"children\": [{\"to\": \"e0cfe17b-1240-5be1-1100-d2976f81d60f\"}], \"actionParametersFetched\": false, \"properties\": {}, \"associatedDocumentUuid\": null, \"type\": \"start-widget\", \"id\": \"3f107997-04cc-8733-60a9-a4bb62cebffc\", \"actionParameters\": []}, {\"name\": \"End\", \"associatedDocumentLoading\": true, \"children\": [], \"actionParametersFetched\": false, \"properties\": {\"body\": \"\", \"cc\": \"\", \"to\": \"\", \"enableMail\": false, \"attachment\": \"\", \"content_type\": \"text/plain\", \"subject\": \"\"}, \"associatedDocumentUuid\": null, \"type\": \"end-widget\", \"id\": \"33430f0f-ebfa-c3ec-f237-3e77efa03d0a\", \"actionParameters\": []}, {\"name\": \"Kill\", \"associatedDocumentLoading\": true, \"children\": [], \"actionParametersFetched\": false, \"properties\": {\"body\": \"\", \"cc\": \"\", \"to\": \"\", \"enableMail\": false, \"message\": \"Action failed, error message[${wf:errorMessage(wf:lastErrorNode())}]\", \"subject\": \"\"}, \"associatedDocumentUuid\": null, \"type\": \"kill-widget\", \"id\": \"17c9c895-5a16-7443-bb81-f34b30b21548\", \"actionParameters\": []}, {\"name\": \"ssh-e0cf\", \"associatedDocumentLoading\": true, \"children\": [{\"to\": \"33430f0f-ebfa-c3ec-f237-3e77efa03d0a\"}, {\"error\": \"17c9c895-5a16-7443-bb81-f34b30b21548\"}], \"actionParametersFetched\": false, \"properties\": {\"ssh_command\": \"bash -x /home/siemanalyst/projects/logs-archive-production/fraud-canada-tokenizedwords/notebooks/x0-execute-fraud-automl.sh ${DATE_YYYYMMDD}\", \"retry_max\": [], \"retry_interval\": [], \"capture_output\": true, \"host\": \"siemanalyst@chpbdaodi02.prod.ch.perform.local\", \"arguments\": [], \"credentials\": [], \"sla\": [{\"value\": false, \"key\": \"enabled\"}, {\"value\": \"${nominal_time}\", \"key\": \"nominal-time\"}, {\"value\": \"\", \"key\": \"should-start\"}, {\"value\": \"${30 * MINUTES}\", \"key\": \"should-end\"}, {\"value\": \"\", \"key\": \"max-duration\"}, {\"value\": \"\", \"key\": \"alert-events\"}, {\"value\": \"\", \"key\": \"alert-contact\"}, {\"value\": \"\", \"key\": \"notification-msg\"}, {\"value\": \"\", \"key\": \"upstream-apps\"}]}, \"associatedDocumentUuid\": null, \"type\": \"ssh-widget\", \"id\": \"e0cfe17b-1240-5be1-1100-d2976f81d60f\", \"actionParameters\": []}], \"id\": 1705, \"nodeNamesMapping\": {\"33430f0f-ebfa-c3ec-f237-3e77efa03d0a\": \"End\", \"e0cfe17b-1240-5be1-1100-d2976f81d60f\": \"ssh-e0cf\", \"3f107997-04cc-8733-60a9-a4bb62cebffc\": \"Start\", \"17c9c895-5a16-7443-bb81-f34b30b21548\": \"Kill\"}, \"uuid\": \"ea9711d1-9c29-22f6-0922-1e9def8b5880\"}}", 
    "is_trashed": false, 
    "name": "Execute - Fraud -  AUTOML - Daily"
  }
}
]
